xolodets/__init__.py
xolodets-0.0.1.dist-info/licenses/LICENSE
xolodets-0.0.1.dist-info/METADATA
xolodets-0.0.1.dist-info/WHEEL
xolodets-0.0.1.dist-info/top_level.txt
xolodets-0.0.1.dist-info/RECORD
