Metadata-Version: 2.4
Name: xolodets
Version: 0.0.1
Summary: Простая библиотека xolodets
Author-email: Nagibator666777 <contact@xolodets.ru>
License: MIT
License-File: LICENSE
Dynamic: license-file
